many_more_routes/__init__.py
many_more_routes/client.py
many_more_routes/construct.py
many_more_routes/ducks.py
many_more_routes/io.py
many_more_routes/methods.py
many_more_routes/models.py
many_more_routes/models.py.bak
many_more_routes/sequence.py
many_more_routes-0.4.10.dist-info/entry_points.txt
many_more_routes-0.4.10.dist-info/LICENSE
many_more_routes-0.4.10.dist-info/WHEEL
many_more_routes-0.4.10.dist-info/METADATA
many_more_routes-0.4.10.dist-info/RECORD
