Metadata-Version: 2.1
Name: many-more-routes
Version: 0.4.10
Summary: Routing tools for the More project
License: GPLv3
Author: Kim TImothy Engh
Author-email: kimothy@users.noreply.github.com
Requires-Python: >=3.9,<4.0
Classifier: License :: Other/Proprietary License
Classifier: Programming Language :: Python :: 3
Classifier: Programming Language :: Python :: 3.10
Classifier: Programming Language :: Python :: 3.9
Requires-Dist: openpyxl (>=3.0.9,<4.0.0)
Requires-Dist: pydantic (>=1.9.1,<2.0.0)
